Workbook

Sheet Hoja1
I3: FECHA DE ELABORACIÓN: | K3: 31 de agosto 2026
I4: EXPEDIENTE No.: | K4: REPORTE_001
B6: CON FUNDAMENTO EN LOS ARITUCULOS 3 FRACCION IV DE LA LEY CONTRATACION PUBLICA DEL ESTADO DE MEXICOY MUNICIPIOS , 17 Y 18 DE SU REGLAMENTO LA DIRECCION DE ADMINISTRACIÓN, A TRAVES DE LA UNIDAD DE ADQUISICIONES Y RECURSOS MATERIALES, DIO INICIO AL ESTUDIO DE MERCADO PARA LA (ADQUISICION O PRESTACION DEL SERVICIO), A FIN DE VERIFICAR LA EXISTENCIA DE (BIEN O SERVICIO), ASI COMO DE (PROVEEDORES O PRESTADORES DE SERVICIOS) A NIVEL (LOCAL, NACIONAL O INTERNACIONAL), PARA ASEGURAR LAS MEJORES CONDICIONES PARA EL MUNICIPIO DE ACAMBAY DE RUIZ CASTAÑEDA EN CUANTO A PRECIO, CALIDAD, OPORTUNIDAD, CANTIDAD, Y DEMAS CARACTERISTICAS SOLICITADAS.
B7: CABE MENCIONAR QUE DICHA (ADQUISICION, O CONTRATACION DEL SERVICIO) SE ENCUENTRA CONSIDERADO EN EL PROGRAMA ANUAL DE ADQUISICIONES Y SERVICIOS 2026
B9: ÁREA ADMINISTRATIVA USUARIA | D9: E00 311 COOR. DESARROLLO COMUNITARIO (DESAYUNOS FRIOS) | H9: CLAVE PROGRAMATICA: | K9: 205060301
B10: PARTIDA PRESUPUESTAL | D10: 1122 SERVICIO DE MONITOREO Y SEGUIMIENTO
B11: OBJETO DE LA CONTRATACIÓN Y/O ADQUISICIÓN: | D11: REALIZAR SERVICIOS DE SEGUIMIENTO
B13: FUENTES CONSULTADAS CON LA FINALIDAD DE DAR CUMPLIMIENTO A LO ESTABLECIDO EN LOS ARTICULOS 17 Y 18 DEL REGLAMENTO DE LA LEY CONTRATACION PUBLICA DEL ESTADO DE MEXICOY MUNICIPIOS, EL DEPARTAMENTO DE ADQUISICIONES REALIZO EL ESTUDIO DE MERCADO PARA DETERMINAR LA EXISTENCIA DE (BIENES O SERVICIOS) Y (PROVEEDORES O PRESTADORES DE SERVICIOS), ASI COMO CONOCER EL PRECIO QUE PREVALECE EN EL MERCADO, ENVIANDO INVITACIONES PARA COTIZAR A:
B15: N.P | C15: PERSONA FISICA O JURIDICO COLECTIVA CONSULTADA | G15: NUMERO TELEFONICO DE CONTACTO | J15: SE ENCUENTRA REGISTRADA EN EL PADRON DE PROVEEDORES DEL MUNICIPIO
B16: 1 | C16: Gabriel Lopez Crisostomo | G16: 7122893019 | J16: SI
B17: 2 | C17: Santiago Lopez Cruz | G17: 8120381738 | J17: SI
B18: 3
B20: DE CONFORMIDAD CON LO ESTABLECIDO EN LA LEY DE CONTRATACION PUBLICA DEL ESTADO DE MEXICO Y MUNICIPIOS Y SU REGLAMENTO, SE LLEVA A CABO LA ELABORACION DE ESTUDIO DE MERCADO, CON LA INFORMACION OBTENIDA DE LAS FUENTES ANTERIORES MENCIONADAS; DETERMINANDO LO SIGUIENTE:
B21: A. CANTIDAD DE LOS (PROVEEDORES O PRESTADORES DE SERVICIO) CONSULTADOS, LOS SIGUIENTES COTIZARON LOS (BIENES O SERVICIOS) SOLICITADOS:
B23: N.P | C23: PERSONA FISICA O JURIDICO COLECTIVA CONSULTADA | G23: NUMERO TELEFONICO DE CONTACTO | J23: CUMPLE
B24: 1 | C24: Gabriel Lopez Crisostomo | G24: 7122893019 | J24: SI
B25: 2 | C25: Santiago Lopez Cruz | G25: 8120381738 | J25: NO
B26: 3
B28: B. CALIDAD DE LOS (PROVEEDORES O PRESTADORES DE SERVICIO) CONSULTADOS, LOS SIGUIENTES CUMPLEN CON LAS ESPECIFICACIONES TECNICAS DE LOS (BIENES O SERVICIOS) SOLICITADOS:
B29: N.P | C29: PERSONA FISICA O JURIDICO COLECTIVA CONSULTADA | G29: NUMERO TELEFONICO DE CONTACTO | J29: CUMPLE
B30: 1 | C30: Gabriel Lopez Crisostomo | G30: 7122893019 | J30: SI
B31: 2 | C31: Santiago Lopez Cruz | G31: 8120381738 | J31: SI
B32: 3
B34: C. OPORTUNIDAD DE LOS (PROVEEDORES O PRESTADORES DE SERVICIO) CONSULTADOS, LOS SIGUIENTES CUMPLEN CON LAS ESPECIFICACIONES ADMINISTRATIVAS Y PARAMETROS DE REFERENCIA, RELATIVOS A LOS (BIENES O SERVICIOS) SOLICITADOS:
B35: N.P | C35: PERSONA FISICA O JURIDICO COLECTIVA CONSULTADA | G35: NUMERO TELEFONICO DE CONTACTO | J35: CUMPLE
B36: 1 | C36: Gabriel Lopez Crisostomo | G36: 7122893019 | J36: SI
B37: 2 | C37: Santiago Lopez Cruz | G37: 8120381738 | J37: NO
B38: 3
B40: ALCANCE: DE ACUERDO CON LAS COTIZACIONES OBTENIDAS, PARA DETERMINAR LA EXISTENCIA DEL (BIEN O SERVICIO) Y DE (PROVEEDORES O PRESTADORES DE SERVICIOS), ASI COMO CONOCER EL PRECIO QUE PREVALECE EN EL MERCADO, SE PRESENTA EL SIGUIENTE ESTUDIO DE MERCADO:
D42: FECHA | F42: COTIZACIÓN 1 | H42: COTIZACIÓN 2 | J42: COTIZACION 3
F43: =C24 -> Gabriel Lopez Crisostomo | H43: =C25 -> Santiago Lopez Cruz
B45: N.P | C45: DESCRIPCION | D45: UNIDAD DE MEDIDA | E45: CANTIDAD | F45: PRECIO UNITARIO | G45: IMPORTE | H45: PRECIO UNITARIO | I45: IMPORTE | J45: PRECIO UNITARIO | K45: IMPORTE | L45: PRECIO PROMEDIO DE REFERENCIA
B46: 1 | C46: SERVICIO DE EXTRACCION | D46: SERVICIO | E46: 3 | F46: 300 | G46: 900 | H46: 100 | I46: 300 | L46: 200
B47: 2 | C47: SERVICIO DE MANEJO | D47: SERVICIO | E47: 3 | F47: 200 | G47: 600 | H47: 200 | I47: 600 | L47: 200
B48: 3 | C48: SERVICIO DE CONSUMO | D48: SERVICIO | E48: 2 | F48: 150 | G48: 300 | H48: 200 | I48: 400 | L48: 175
B49: 4 | G49: =F49*E49 -> 0 | I49: =H49*E49 -> 0 | L49: =(F49+H49+J49)/2 -> 0
F50: SUBTOTAL | G50: 1800 | H50: SUBTOTAL | I50: 1300 | J50: SUBTOTAL | L50: =(G50+I50)/2 -> 1550
F51: I.V.A. | G51: 288 | I51: 208
F52: TOTAL | G52: 2088 | H52: TOTAL | I52: 1508 | J52: TOTAL | L52: 1798
B54: N.P | C54: CONDICIONES COMERCIALES | G54: CUMPLEN CON LAS CONDICIONES COMERCIALES (SI/NO)
G55: =F43 -> Gabriel Lopez Crisostomo | I55: =H43 -> Santiago Lopez Cruz | K55: =J43 -> 0
B56: LUGAR DE ENTREGA DE LOS BIENES Y/O SERVICIOS: | C56: DIF | K56: =J38 -> 0
B57: PLAZO DE ENTREGA O VIGENCIA: | C57: 5 DIAS | K57: =K56 -> 0
B58: FORMA DE PAGO: | C58: TESORERIA | K58: =K57 -> 0
B59: FUNDAMENTO EN LOS ARTÍCULOS 17 Y 18 DEL REGLAMENTO DE LA LEY DE CONTRATACIÓN PÚBLICA DEL ESTADO DE MÉXICO Y MUNICIPIOS.: Artículo 18.- Los precios de referencia se determinarán mediante el promedio de al menos dos cotizaciones de los fabricantes, distribuidores o comercializadoras y cámaras del ramo correspondiente, que se deberán obtener por escrito, o a través de los medios electrónicos disponibles o mediante el estudio de precios, considerando las mismas condiciones en cuanto a cantidades, plazos y lugares de entrega de los bienes o de la prestación de los servicios, la forma y términos de pago, las características técnicas de los bienes o servicios y las demás condiciones que resulten aplicables y que permitan una comparación objetiva. Cuando no se puedan obtener las cotizaciones referidas en el párrafo anterior, por razones de titularidad de patentes, registros, derechos de autor o derechos exclusivos; mantenimientos correctivos; o porque las empresas o particulares no tengan interés en emitirlas; o bien, porque el área usuaria no lo considere conveniente por motivos de confidencialidad de la información o porque ponga en riesgo la seguridad del Estado, se podrá utilizar como precio de mercado el monto comprometido señalado en las solicitudes de adquisiciones de bienes o servicios, que se haya determinado con base en documentos de índole comercial, relacionados con bienes o servicios similares que tengan registrados las unidades administrativas solicitantes.
B61: EL PRECIO DE REFERENCIA CON IVA INCLUIDO OBTENIDO EN EL ESTUDIO DE MERCADO ASCIENDE A LA CANTIDAD DE: | H61: =I52 -> 1508 | I61: MIL QUINIENTOS OCHO PESOS 00/100 M.N.
B63: RESULTADO DEL ESTUDIO DE MERCADO Y AUTORIZACION DE INICIACIÓN DEL PROCEDIMIENTO ADQUISITIVO
B64: PRIMERO. EXISTENCIA DE PROVEEDORES. EL ESTUDIO DE MERCADO ACREDITA LA EXISTENCIA DE AL MENOS DOS PROVEEDORES Y/O PRESTADORES DE SERVICIOS EN EL MERCADO CON CAPACIDAD PARA SUMINISTRAR LOS BIENES O SERVICIOS REQUERIDOS. EL PROVEEDOR O PRESTADOR DE SERVICIOS QUE REÚNE LA INTEGRALIDAD DE LOS REQUISITOS TÉCNICOS Y OFRECE LAS MEJORES CONDICIONES FINANCIERAS ES EL SIGUIENTE:
B66: NOMBRE O RAZÓN SOCIAL: | C66: Santiago Lopez Cruz | F66: RFC | G66: HSG782HS | H66: DOMICILIO: | I66: SAN JUAN COAJOMULCO
B68: SEGUNDO. PRECIO RAZONABLE Y DE MERCADO. SE ENCUENTRA DENTRO DEL RANGO DE PRECIOS VERIFICADO MEDIANTE LAS FUENTES CONSULTADAS, NO EXCEDE EL UMBRAL DE $500,000.00 M.N. ESTABLECIDO PARA ADJUDICACIÓN DIRECTA, Y RESULTA EL MÁS COMPETITIVO ENTRE LOS PROVEEDORES QUE CUMPLEN LOS REQUISITOS TÉCNICOS.
B69: EL PRECIO TOTAL OFERTADO DE: | E69: =H61 -> 1508 | F69: =I61 -> MIL QUINIENTOS OCHO PESOS 00/100 M.N.
B71: TERCERO. DERIVADO DE LO ANTERIOR, CON BASE EN LOS ARTICULOS 48 FRACCIÓN XI DE LA LEY DE CONTRATACION PUBLICA DEL ESTADO DE MEXICO Y MUNICIPIOS Y SU REGLAMENTO, Y LOS MONTOS PUBLICADOS EN EL PRESUPUESTO DE EGRESOS DEL GOBIERNO DEL ESTADO DE MÉXICO PARA EL EJERCICIO FISCAL 2026, PARA LLEVAR A CABO LOS PROCEDIMIENTOS DE ADQUISICION DE BIENES Y/O CONTRATACION DE SERVICIOS EN SUS DISTINTAS MODALIDADES, CORRESPONDIENTES AL EJERCICIO FISCAL 2026, SE DETERMINA QUE EL PROCEDIMIENTO DE ADQUISITIVO QUE SE LLEVARA A CABO SERA MEDIANTE LA SIGUIENTE MODALIDAD:
B72: TIPO DE PROCEDIMIENTO: ADJUDICACION POR CONTRATO
B74: QUINTO – DETERMINACIÓN: CON BASE EN LOS RESULTADOS DEL PRESENTE ESTUDIO DE MERCADO, ESTA DIRECCIÓN DE ADMINISTRACIÓN DETERMINA PROCEDENTE LA ADJUDICACIÓN DIRECTA AL SIGUIENTE PROVEEDOR O PRESTADOR DE SERVICIOS, AL AMPARO DEL ARTÍCULO 48, FRACCIÓN XI DE LA LEY DE CONTRATACIÓN PÚBLICA DEL ESTADO DE MÉXICO Y MUNICIPIOS.
B75: NOMBRE O RAZÓN SOCIAL: | C75: =C66 -> Santiago Lopez Cruz | F75: RFC | G75: =G66 -> HSG782HS | H75: DOMICILIO: | I75: =I66 -> SAN JUAN COAJOMULCO
B76: EL PRECIO TOTAL CON IMPUESTOS APLICABLES CORRESPONDIENTE DE: | E76: =E69 -> 1508 | F76: =F69 -> MIL QUINIENTOS OCHO PESOS 00/100 M.N.
B77: ÁREA ADMINISTRATIVA SOLICITANTE: | D77: E00 311 COOR. DESARROLLO COMUNITARIO (DESAYUNOS FRIOS) | I77: CLAVE PROGRAMATICA | L77: 205060301
B78: PARTIDA PRESUPUESTAL | D78: 1122 SERVICIO DE MONITOREO Y SEGUIMIENTO
B80: SEXTO – EXPUESTO LO ANTERIOR, ESTA DIRECCIÓN DE ADMINISTRACIÓN AUTORIZA DAR INICIO AL PROCEDICIENTO DE ADQUISICIÓN DE BIENES O CONTRATACIÓN DE SERVICIOS AL TITULAR DE LA UNIDAD DE ADQUISICIONES Y RECURSOS MATERIALES DANDO CUMPLIMIENTO A LO ESTABLECIDO EN LA LEY DE CONTRATACIÓN PÚBLICA DEL ESTADO DE MÉXICO Y MUNICIPIOS Y SU REGLAMENTO.
B82: ELABORÓ | E82: REVISÓ | J82: AUTORIZÓ
B83: C. ANA LAURA ANTONIO MATEO AUXILIAR DE ADMINISTRACIÓN | E83: MTRA. YARASHED MARTÍNEZ SÁNCHEZ | J83: LIC. DANIELA POPOCA RIVERA
E84: COORDINADORA DE ADMINISTRACIÓN | J84: DIRECTORA DEL SMDIF SAN FELIPE DEL PROGRESO
B85: Con fundamento en los artículos 17 y 18 del Reglamento de la Ley de Contratación Pública del Estado de México y Municipios.

Sheet Hoja2
B8: Toluca a | D8: 7 de agosto de 2026.
A10: SISTEMA MUNICIPAL DIF DE SAN FELIPE DEL PROGRESO
A11: MTRA. YARASHED MARTÍNEZ SÁNCHEZ
A12: COORDINADORA DE ADMINISTRACIÓN
A13: PRESENTE
A14: POR MEDIO DEL PRESENTE RECIBA UN CORDIAL SALUDO, ASÍ MISMO ENVIAMOS LA SIGUIENTE:
A16: COTIZACIÓN
A18: UNIDAD DE MEDIDA | B18: CONCEPTO | C18: CANTIDAD | D18: COSTO UNITARIO | E18: IMPORTE
B19: =Hoja1!C46 -> SERVICIO DE EXTRACCION | D19: =Hoja1!F46 -> 300 | E19: =C19*D19 -> 0
B20: =Hoja1!C47 -> SERVICIO DE MANEJO | D20: =Hoja1!F47 -> 200 | E20: =C20*D20 -> 0
B21: =Hoja1!C48 -> SERVICIO DE CONSUMO | D21: =Hoja1!F48 -> 150 | E21: =C21*D21 -> 0
B22: =Hoja1!C49 -> 0 | D22: =Hoja1!F49 -> 0 | E22: =C22*D22 -> 0
A23: IMPORTE CON LETRA: | D23: SUBTOTAL | E23: =SUM(E19:E22) -> 0
A24: CINCO MIL DOSCIENTOS VEINTE PESOS 00/100 M.N. | D24: I.V.A.
D25: TOTAL | E25: =SUM(E23:E24) -> 0
A27: CONDICIONES COMERCIALES:
A29: LUGAR DE LA PRESTACIÓN DEL SERVICIO O ENTREGA DE BIENES:
A31: FORMA DE PAGO:
A33: PLAZO DE ENTREGA DE LOS BIENES Y/O SERVICIOS:
A34: DENTRO DE LOS 30 DIAS HABILES POSTERIORES A LA CONFIRMACIÓN DEL PEDIDO O FIRMA DEL CONTRATO.
A35: VIGENCIA DE LA COTIZACIÓN:
A36: 45 DIAS POSTERIORES A SU EMISIÓN
A38: SIN MAS POR EL MOMENTO Y EN ESPERA DE VERNOS FAVORECIDO QUEDO DE USTED.
B40: ATENTAMENTE
